waldiez/__init__.py
waldiez/__main__.py
waldiez/_version.py
waldiez/cli.py
waldiez/exporter.py
waldiez/logger.py
waldiez/py.typed
waldiez/runner.py
waldiez/cli_extras/__init__.py
waldiez/cli_extras/jupyter.py
waldiez/cli_extras/runner.py
waldiez/cli_extras/studio.py
waldiez/exporting/__init__.py
waldiez/exporting/agent/__init__.py
waldiez/exporting/agent/code_execution.py
waldiez/exporting/agent/exporter.py
waldiez/exporting/agent/factory.py
waldiez/exporting/agent/processor.py
waldiez/exporting/agent/system_message.py
waldiez/exporting/agent/termination.py
waldiez/exporting/agent/extras/__init__.py
waldiez/exporting/agent/extras/captain_agent_extras.py
waldiez/exporting/agent/extras/doc_agent_extras.py
waldiez/exporting/agent/extras/group_manager_agent_extras.py
waldiez/exporting/agent/extras/group_member_extras.py
waldiez/exporting/agent/extras/rag_user_proxy_agent_extras.py
waldiez/exporting/agent/extras/reasoning_agent_extras.py
waldiez/exporting/agent/extras/handoffs/__init__.py
waldiez/exporting/agent/extras/handoffs/after_work.py
waldiez/exporting/agent/extras/handoffs/available.py
waldiez/exporting/agent/extras/handoffs/condition.py
waldiez/exporting/agent/extras/handoffs/handoff.py
waldiez/exporting/agent/extras/handoffs/target.py
waldiez/exporting/agent/extras/rag/__init__.py
waldiez/exporting/agent/extras/rag/chroma_extras.py
waldiez/exporting/agent/extras/rag/mongo_extras.py
waldiez/exporting/agent/extras/rag/pgvector_extras.py
waldiez/exporting/agent/extras/rag/qdrant_extras.py
waldiez/exporting/agent/extras/rag/vector_db_extras.py
waldiez/exporting/chats/__init__.py
waldiez/exporting/chats/exporter.py
waldiez/exporting/chats/factory.py
waldiez/exporting/chats/processor.py
waldiez/exporting/chats/utils/__init__.py
waldiez/exporting/chats/utils/common.py
waldiez/exporting/chats/utils/group.py
waldiez/exporting/chats/utils/nested.py
waldiez/exporting/chats/utils/sequential.py
waldiez/exporting/chats/utils/single.py
waldiez/exporting/core/__init__.py
waldiez-0.7.1.dist-info/METADATA
waldiez-0.7.1.dist-info/WHEEL
waldiez-0.7.1.dist-info/entry_points.txt
waldiez-0.7.1.dist-info/licenses/LICENSE
waldiez-0.7.1.dist-info/licenses/NOTICE.md
waldiez-0.7.1.dist-info/RECORD
