Metadata-Version: 2.4
Name: waldiez
Version: 0.7.1
Dynamic: Keywords
Summary: Make AG2 Agents Collaborate: Drag, Drop, and Orchestrate with Waldiez.
Project-URL: Homepage, https://waldiez.io
Project-URL: Bug Tracker, https://github.com/waldiez/waldiez/issues
Project-URL: Repository, https://github.com/waldiez/waldiez.git
Author-email: Panagiotis Kasnesis <pkasnesis@waldiez.io>, Lazaros Toumanidis <laztoum@waldiez.io>, Christos Chatzigeorgiou <chrihatz@waldiez.io>
License-File: LICENSE
License-File: NOTICE.md
Classifier: Development Status :: 4 - Beta
Classifier: Framework :: Pydantic :: 2
Classifier: Intended Audience :: Developers
Classifier: Intended Audience :: Education
Classifier: Intended Audience :: Science/Research
Classifier: License :: OSI Approved :: Apache Software License
Classifier: Operating System :: OS Independent
Classifier: Programming Language :: Python
Classifier: Programming Language :: Python :: 3
Classifier: Programming Language :: Python :: 3.10
Classifier: Programming Language :: Python :: 3.11
Classifier: Programming Language :: Python :: 3.12
Classifier: Programming Language :: Python :: 3.13
Classifier: Programming Language :: Python :: 3.14
Classifier: Topic :: Scientific/Engineering
Classifier: Topic :: Scientific/Engineering :: Artificial Intelligence
Classifier: Topic :: Software Development :: Code Generators
Classifier: Typing :: Typed
Requires-Python: >=3.10
Requires-Dist: ag2[openai]==0.10.3
Requires-Dist: aiocsv==1.4.0
Requires-Dist: aiofiles==25.1.0
Requires-Dist: aiosqlite==0.22.1
Requires-Dist: click==8.3.1
Requires-Dist: graphviz<=0.21
Requires-Dist: httpx<1
Requires-Dist: jupytext
Requires-Dist: nest-asyncio==1.6.0
Requires-Dist: numpy>2
Requires-Dist: packaging==25.0
Requires-Dist: pandas>=2
Requires-Dist: parso==0.8.5
Requires-Dist: pillow
Requires-Dist: pip>=25.1
Requires-Dist: platformdirs==4.5.1
Requires-Dist: psutil==7.2.1
Requires-Dist: pydantic<3,>=2.10
Requires-Dist: rpds-py==0.30.0
Requires-Dist: typer<1,>=0.18.0
Provides-Extra: ag2-extras
Requires-Dist: ag2[a2a]==0.10.3; extra == 'ag2-extras'
Requires-Dist: ag2[anthropic]==0.10.3; extra == 'ag2-extras'
Requires-Dist: ag2[autobuild]==0.10.3; (python_version < '3.14') and extra == 'ag2-extras'
Requires-Dist: ag2[bedrock]==0.10.3; extra == 'ag2-extras'
Requires-Dist: ag2[cohere]==0.10.3; extra == 'ag2-extras'
Requires-Dist: ag2[commsagent-discord]==0.10.3; extra == 'ag2-extras'
Requires-Dist: ag2[commsagent-slack]==0.10.3; extra == 'ag2-extras'
Requires-Dist: ag2[commsagent-telegram]==0.10.3; extra == 'ag2-extras'
Requires-Dist: ag2[crawl4ai]==0.10.3; extra == 'ag2-extras'
Requires-Dist: ag2[duckduckgo]==0.10.3; extra == 'ag2-extras'
Requires-Dist: ag2[gemini-realtime]==0.10.3; (sys_platform != 'win32') and extra == 'ag2-extras'
Requires-Dist: ag2[gemini-realtime]==0.10.3; (sys_platform == 'win32' and platform_machine != 'arm64' and platform_machine != 'aarch64' and platform_machine != 'ARM64' and platform_machine != 'AARCH64') and extra == 'ag2-extras'
Requires-Dist: ag2[gemini]==0.10.3; (sys_platform != 'win32') and extra == 'ag2-extras'
Requires-Dist: ag2[gemini]==0.10.3; (sys_platform == 'win32' and platform_machine != 'arm64' and platform_machine != 'aarch64' and platform_machine != 'ARM64' and platform_machine != 'AARCH64') and extra == 'ag2-extras'
Requires-Dist: ag2[google-api]==0.10.3; extra == 'ag2-extras'
Requires-Dist: ag2[google-client]==0.10.3; extra == 'ag2-extras'
Requires-Dist: ag2[google-search]==0.10.3; extra == 'ag2-extras'
Requires-Dist: ag2[graph]==0.10.3; extra == 'ag2-extras'
Requires-Dist: ag2[groq]==0.10.3; extra == 'ag2-extras'
Requires-Dist: ag2[interop-crewai]==0.10.3; extra == 'ag2-extras'
Requires-Dist: ag2[interop-langchain]==0.10.3; extra == 'ag2-extras'
Requires-Dist: ag2[interop-pydantic-ai]==0.10.3; extra == 'ag2-extras'
Requires-Dist: ag2[lmm]==0.10.3; extra == 'ag2-extras'
Requires-Dist: ag2[long-context]==0.10.3; extra == 'ag2-extras'
Requires-Dist: ag2[mcp]==0.10.3; extra == 'ag2-extras'
Requires-Dist: ag2[mistral]==0.10.3; extra == 'ag2-extras'
Requires-Dist: ag2[neo4j]==0.10.3; (sys_platform != 'win32') and extra == 'ag2-extras'
Requires-Dist: ag2[neo4j]==0.10.3; (sys_platform == 'win32' and platform_machine != 'arm64' and platform_machine != 'aarch64' and platform_machine != 'ARM64' and platform_machine != 'AARCH64') and extra == 'ag2-extras'
Requires-Dist: ag2[ollama]==0.10.3; extra == 'ag2-extras'
Requires-Dist: ag2[openai-realtime]==0.10.3; extra == 'ag2-extras'
Requires-Dist: ag2[rag]==0.10.3; (python_version < '3.14') and extra == 'ag2-extras'
Requires-Dist: ag2[redis]==0.10.3; extra == 'ag2-extras'
Requires-Dist: ag2[retrievechat-couchbase]==0.10.3; (python_version < '3.14') and extra == 'ag2-extras'
Requires-Dist: ag2[retrievechat-mongodb]==0.10.3; (python_version < '3.14') and extra == 'ag2-extras'
Requires-Dist: ag2[retrievechat-pgvector]==0.10.3; (python_version < '3.14') and extra == 'ag2-extras'
Requires-Dist: ag2[retrievechat-qdrant]==0.10.3; (python_version < '3.14') and extra == 'ag2-extras'
Requires-Dist: ag2[retrievechat]==0.10.3; (python_version < '3.14') and extra == 'ag2-extras'
Requires-Dist: ag2[tavily]==0.10.3; extra == 'ag2-extras'
Requires-Dist: ag2[together]==0.10.3; (sys_platform != 'win32') and extra == 'ag2-extras'
Requires-Dist: ag2[together]==0.10.3; (sys_platform == 'win32' and platform_machine != 'arm64' and platform_machine != 'aarch64' and platform_machine != 'ARM64' and platform_machine != 'AARCH64') and extra == 'ag2-extras'
Requires-Dist: ag2[twilio]==0.10.3; extra == 'ag2-extras'
Requires-Dist: ag2[websockets]==0.10.3; extra == 'ag2-extras'
Requires-Dist: ag2[websurfer]==0.10.3; extra == 'ag2-extras'
Requires-Dist: ag2[wikipedia]==0.10.3; extra == 'ag2-extras'
Provides-Extra: dev
Requires-Dist: ag2[redis]==0.10.3; extra == 'dev'
Requires-Dist: autoflake==2.3.1; extra == 'dev'
Requires-Dist: bandit==1.9.2; extra == 'dev'
Requires-Dist: basedpyright==1.37.1; extra == 'dev'
Requires-Dist: black[jupyter]==25.12.0; extra == 'dev'
Requires-Dist: build==1.4.0; extra == 'dev'
Requires-Dist: fakeredis==2.33.0; extra == 'dev'
Requires-Dist: fastjsonschema>=2.21.2; extra == 'dev'
Requires-Dist: flake8==7.3.0; extra == 'dev'
Requires-Dist: hatchling==1.28.0; extra == 'dev'
Requires-Dist: jsonschema==4.26.0; extra == 'dev'
Requires-Dist: jupyter-server==2.17.0; extra == 'dev'
Requires-Dist: jupyterlab==4.5.2; extra == 'dev'
Requires-Dist: mypy-extensions>=1.1.0; extra == 'dev'
Requires-Dist: mypy==1.19.1; extra == 'dev'
Requires-Dist: nbclient>=0.10.4; extra == 'dev'
Requires-Dist: nbconvert>=7.16.6; extra == 'dev'
Requires-Dist: nbformat>=5.10.4; extra == 'dev'
Requires-Dist: nodeenv>=1.10.0; extra == 'dev'
Requires-Dist: notebook-shim>=0.2.4; extra == 'dev'
Requires-Dist: paho-mqtt<3.0,>=2.1.0; extra == 'dev'
Requires-Dist: pandas-stubs==2.3.3.251219; extra == 'dev'
Requires-Dist: prek==0.2.27; extra == 'dev'
Requires-Dist: pydocstyle==6.3.0; extra == 'dev'
Requires-Dist: pylint==4.0.4; extra == 'dev'
Requires-Dist: python-dotenv==1.2.1; extra == 'dev'
Requires-Dist: ruff==0.14.11; extra == 'dev'
Requires-Dist: toml==0.10.2; (python_version <= '3.10') and extra == 'dev'
Requires-Dist: tox==4.34.1; extra == 'dev'
Requires-Dist: types-aiofiles==25.1.0.20251011; extra == 'dev'
Requires-Dist: types-jsonschema==4.26.0.20260109; extra == 'dev'
Requires-Dist: types-psutil==7.2.1.20251231; extra == 'dev'
Requires-Dist: types-pyyaml==6.0.12.20250915; extra == 'dev'
Requires-Dist: types-redis==4.6.0.20241004; extra == 'dev'
Requires-Dist: types-requests==2.32.4.20260107; extra == 'dev'
Requires-Dist: types-toml==0.10.8.20240310; extra == 'dev'
Requires-Dist: watchdog>=5.0.0; extra == 'dev'
Requires-Dist: websockets<16,>=14.0; extra == 'dev'
Requires-Dist: yamllint==1.38.0; extra == 'dev'
Provides-Extra: docs
Requires-Dist: markdown-callouts==0.4.0; extra == 'docs'
Requires-Dist: mdx-include==1.4.2; extra == 'docs'
Requires-Dist: mdx-truly-sane-lists==1.3; extra == 'docs'
Requires-Dist: mkdocs-autorefs==1.4.3; extra == 'docs'
Requires-Dist: mkdocs-awesome-nav==3.3.0; extra == 'docs'
Requires-Dist: mkdocs-jupyter==0.25.1; extra == 'docs'
Requires-Dist: mkdocs-macros-plugin==1.5.0; extra == 'docs'
Requires-Dist: mkdocs-material==9.7.1; extra == 'docs'
Requires-Dist: mkdocs-minify-html-plugin; (python_version == '3.10' and sys_platform == 'win32' and platform_machine == 'AARCH64') and extra == 'docs'
Requires-Dist: mkdocs-minify-html-plugin; (python_version == '3.10' and sys_platform == 'win32' and platform_machine == 'ARM64') and extra == 'docs'
Requires-Dist: mkdocs-minify-html-plugin; (python_version == '3.10' and sys_platform == 'win32' and platform_machine == 'aarch64') and extra == 'docs'
Requires-Dist: mkdocs-minify-html-plugin; (python_version == '3.10' and sys_platform == 'win32' and platform_machine == 'arm64') and extra == 'docs'
Requires-Dist: mkdocs-minify-html-plugin==0.3.9; (python_version <= '3.13' and sys_platform != 'win32') and extra == 'docs'
Requires-Dist: mkdocs-minify-html-plugin==0.3.9; (python_version == '3.10' and sys_platform == 'win32' and platform_machine != 'arm64' and platform_machine != 'aarch64' and platform_machine != 'ARM64' and platform_machine != 'AARCH64') and extra == 'docs'
Requires-Dist: mkdocs-minify-html-plugin==0.3.9; (python_version >= '3.11') and extra == 'docs'
Requires-Dist: mkdocs-open-in-new-tab==1.0.8; extra == 'docs'
Requires-Dist: mkdocs==1.6.1; extra == 'docs'
Requires-Dist: mkdocstrings-crystal==0.3.9; extra == 'docs'
Requires-Dist: mkdocstrings-python==2.0.1; extra == 'docs'
Requires-Dist: mkdocstrings[crystal,python]==1.0.0; extra == 'docs'
Requires-Dist: natsort==8.4.0; extra == 'docs'
Provides-Extra: jupyter
Requires-Dist: ipywidgets==8.1.8; extra == 'jupyter'
Requires-Dist: jupyter-server==2.17.0; extra == 'jupyter'
Requires-Dist: jupyterlab==4.5.2; extra == 'jupyter'
Requires-Dist: waldiez-jupyter==0.7.1; extra == 'jupyter'
Provides-Extra: mqtt
Requires-Dist: paho-mqtt<3.0,>=2.1.0; extra == 'mqtt'
Provides-Extra: redis
Requires-Dist: ag2[redis]==0.10.3; extra == 'redis'
Provides-Extra: reload
Requires-Dist: watchdog>=5.0.0; extra == 'reload'
Provides-Extra: runner
Requires-Dist: waldiez-runner==0.7.1; (python_version >= '3.11') and extra == 'runner'
Provides-Extra: studio
Requires-Dist: waldiez-studio==0.7.1; extra == 'studio'
Provides-Extra: test
Requires-Dist: ag2[redis]==0.10.3; extra == 'test'
Requires-Dist: ag2[websockets]==0.10.3; extra == 'test'
Requires-Dist: fakeredis==2.33.0; extra == 'test'
Requires-Dist: paho-mqtt<3.0,>=2.1.0; extra == 'test'
Requires-Dist: pytest-asyncio==1.3.0; extra == 'test'
Requires-Dist: pytest-cov==7.0.0; extra == 'test'
Requires-Dist: pytest-env==1.2.0; extra == 'test'
Requires-Dist: pytest-html==4.1.1; extra == 'test'
Requires-Dist: pytest-sugar==1.1.1; extra == 'test'
Requires-Dist: pytest-timeout==2.4.0; extra == 'test'
Requires-Dist: pytest-xdist==3.8.0; extra == 'test'
Requires-Dist: pytest==9.0.2; extra == 'test'
Requires-Dist: tox==4.34.1; extra == 'test'
Requires-Dist: watchdog>=5.0.0; extra == 'test'
Requires-Dist: websockets<16,>=14.0; extra == 'test'
Provides-Extra: websockets
Requires-Dist: websockets<16,>=14.0; extra == 'websockets'
